django_safe_settings/__init__.py
django_safe_settings/patch.py
django_safe_settings/settings.py
django_safe_settings/management/__init__.py
django_safe_settings/management/commands/__init__.py
django_safe_settings/management/commands/django_safe_settings_encrypt.py
django_safe_settings/migrations/__init__.py
django_safe_settings-0.1.5.dist-info/licenses/LICENSE
django_safe_settings-0.1.5.dist-info/METADATA
django_safe_settings-0.1.5.dist-info/WHEEL
django_safe_settings-0.1.5.dist-info/top_level.txt
django_safe_settings-0.1.5.dist-info/RECORD
